dcm_spec_tools/__init__.py
dcm_spec_tools/dump_dcm_info.py
dcm_spec_tools/tag_tools.py
dcm_spec_tools/validate_iods.py
dcm_spec_tools/spec_reader/__init__.py
dcm_spec_tools/spec_reader/condition.py
dcm_spec_tools/spec_reader/condition_parser.py
dcm_spec_tools/spec_reader/edition_reader.py
dcm_spec_tools/spec_reader/part3_reader.py
dcm_spec_tools/spec_reader/part4_reader.py
dcm_spec_tools/spec_reader/part6_reader.py
dcm_spec_tools/spec_reader/serializer.py
dcm_spec_tools/spec_reader/spec_reader.py
dcm_spec_tools/spec_reader/tests/__init__.py
dcm_spec_tools/spec_reader/tests/test_condition.py
dcm_spec_tools/spec_reader/tests/test_condition_parser.py
dcm_spec_tools/spec_reader/tests/test_edition_reader.py
dcm_spec_tools/spec_reader/tests/test_part3_reader.py
dcm_spec_tools/spec_reader/tests/test_part4_reader.py
dcm_spec_tools/spec_reader/tests/test_part6_reader.py
dcm_spec_tools/spec_reader/tests/test_spec_reader.py
dcm_spec_tools/tests/__init__.py
dcm_spec_tools/tests/test_utils.py
dcm_spec_tools/validator/__init__.py
dcm_spec_tools/validator/dicom_file_validator.py
dcm_spec_tools/validator/iod_validator.py
dcm_spec_tools/validator/tests/__init__.py
dcm_spec_tools/validator/tests/test_dicom_file_validator.py
dcm_spec_tools/validator/tests/test_iod_validator.py
dcm_spec_tools-0.3.1.dist-info/LICENSE
dcm_spec_tools-0.3.1.dist-info/METADATA
dcm_spec_tools-0.3.1.dist-info/WHEEL
dcm_spec_tools-0.3.1.dist-info/entry_points.txt
dcm_spec_tools-0.3.1.dist-info/top_level.txt
dcm_spec_tools-0.3.1.dist-info/RECORD
