Metadata-Version: 2.1
Name: dcm-spec-tools
Version: 0.3.1
Summary: Python DICOM tools using input from DICOM specs in docbook format
Home-page: http://github.com/mrbean-bremen/dcm-spec-tools
Author: mrbean-bremen
Author-email: hansemrbean@googlemail.com
License: UNKNOWN
Keywords: dicom python
Platform: UNKNOWN
Classifier: License :: OSI Approved :: MIT License
Classifier: Intended Audience :: Developers
Classifier: Intended Audience :: Healthcare Industry
Classifier: Development Status :: 2 - Pre-Alpha
Classifier: Environment :: Console
Classifier: Programming Language :: Python
Classifier: Programming Language :: Python :: 3.5
Classifier: Programming Language :: Python :: 3.6
Classifier: Programming Language :: Python :: 3.7
Classifier: Operating System :: POSIX :: Linux
Classifier: Operating System :: MacOS
Classifier: Operating System :: Microsoft :: Windows
Classifier: Topic :: Scientific/Engineering :: Medical Science Apps.
Requires-Dist: pydicom
